pylazybam/__init__.py
pylazybam/bam.py
pylazybam/bgzf.py
pylazybam/decoders.py
pylazybam/tags.py
pylazybam/tests/__init__.py
pylazybam/tests/test_all.py
pylazybam/tests/test_bam.py
pylazybam-0.1.0.dist-info/LICENSE
pylazybam-0.1.0.dist-info/METADATA
pylazybam-0.1.0.dist-info/WHEEL
pylazybam-0.1.0.dist-info/entry_points.txt
pylazybam-0.1.0.dist-info/top_level.txt
pylazybam-0.1.0.dist-info/zip-safe
pylazybam-0.1.0.dist-info/RECORD
