Metadata-Version: 2.1
Name: pylazybam
Version: 0.1.0
Summary: pylazybam - a pure python bam parser for rapid content based read sorting
Home-page: https://git@bitbucket.org/genomematt/pylazybam.git
Author: Matthew Wakefield
Author-email: matthew.wakefield@unimelb.edu.au
License: BSD
Platform: UNKNOWN
Classifier: Development Status :: 4 - Beta
Classifier: License :: OSI Approved :: BSD License
Classifier: Operating System :: POSIX
Classifier: Programming Language :: Python :: 3.7
Classifier: Programming Language :: Python :: 3.8
Classifier: Topic :: Scientific/Engineering :: Bio-Informatics
Requires-Dist: setuptools (>=1.1.6)
